nanome/__init__.py
nanome/common/__init__.py
nanome/common/eval_common.py
nanome/common/global_config.py
nanome/common/global_settings.py
nanome/common/nanome_genome_annotation.csv
nanome/nanocompare/__init__.py
nanome/nanocompare/benchmarkingDataConstruct.py
nanome/nanocompare/computeRawReadsCoverage.py
nanome/nanocompare/cov_accuracy_eval.py
nanome/nanocompare/join_preds_eval.py
nanome/nanocompare/nanome_tool.py
nanome/nanocompare/newtool_parser.py
nanome/nanocompare/pcc_region_eval.py
nanome/nanocompare/plot_figure.py
nanome/nanocompare/read_level_eval.py
nanome/nanocompare/region_intersect.py
nanome/nanocompare/site_level_eval.py
nanome/nanocompare/tss_eval.py
nanome/nanocompare/report/__init__.py
nanome/nanocompare/report/gen_html_report.py
nanome/nanocompare/report/gen_txt_readme.py
nanome/nanocompare/utils/__init__.py
nanome/nanocompare/utils/combine_output_na12878.py
nanome/nanocompare/utils/distribution_influnce_genomic_context.py
nanome/nanocompare/utils/meth_stats_tool.py
nanome/nanocompare/utils/nanopore_data_longread_portion_stats.py
nanome/nanocompare/utils/parse_urls_input_na12878.py
nanome/nanocompare/utils/sanity_5hmc/__init__.py
nanome/nanocompare/utils/sanity_5hmc/sanity_check_5hmc.py
nanome/other/__init__.py
nanome/other/io/__init__.py
nanome/other/io/build_fast5_readid_db.py
nanome/other/phasing/__init__.py
nanome/other/phasing/hp_split.py
nanome/other/phasing/mega_parser.py
nanome/other/phasing/methcall2bed.py
nanome/other/phasing/nanomethphase.py
nanome/xgboost/__init__.py
nanome/xgboost/cs_agg_site.py
nanome/xgboost/cs_eval_read.py
nanome/xgboost/cs_eval_site.py
nanome/xgboost/cs_predict.py
nanome/xgboost/cs_train.py
nanome/xgboost/ml_common.py
nanome/xgboost/xgboost_eval.py
nanome/xgboost/xgboost_predict.py
nanome/xgboost/xgboost_prepdata.py
nanome/xgboost/xgboost_train.py
nanome/xgboost/trained_model/NA12878_chr1_xgboost_basic_model.pkl
nanome/xgboost/trained_model/NA12878_chr1_xgboost_basic_w_model.pkl
nanome_jax-2.0.11.dist-info/LICENSE
nanome_jax-2.0.11.dist-info/METADATA
nanome_jax-2.0.11.dist-info/WHEEL
nanome_jax-2.0.11.dist-info/top_level.txt
nanome_jax-2.0.11.dist-info/RECORD
