Metadata-Version: 2.1
Name: nanome-jax
Version: 2.0.11
Summary: NANOME (Nanopore methylation) pipeline developed by Li Lab at The Jackson Laboratory
Home-page: https://github.com/LabShengLi/nanome
Author: Yang Liu
Author-email: yang.liu@jax.org
License: MIT License
Project-URL: Bug Tracker, https://github.com/LabShengLi/nanome/issues
Classifier: Programming Language :: Python :: 3
Classifier: Intended Audience :: Science/Research
Classifier: License :: OSI Approved :: MIT License
Classifier: Operating System :: OS Independent
Requires-Python: >=3.6
License-File: LICENSE
Requires-Dist: biopython
Requires-Dist: pybedtools (>=0.8.2)
Requires-Dist: pandas
Requires-Dist: seaborn
Requires-Dist: scipy
Requires-Dist: numpy
Requires-Dist: statsmodels
Requires-Dist: scikit-learn
Requires-Dist: matplotlib
Requires-Dist: jinja2
Requires-Dist: openpyxl
Requires-Dist: h5py
Requires-Dist: tqdm
Requires-Dist: joblib
Requires-Dist: psutil
Requires-Dist: xgboost
Requires-Dist: pytabix
Requires-Dist: pysam
Requires-Dist: ont-fast5-api
